{
  "updateTime": "2026-02-18T14:27:17.271Z",
  "xam": {
    "numbers": [
      28,
      42,
      22,
      49,
      12,
      31,
      13
    ],
    "issue": "2026049",
    "time": "2026-02-18 21:32:32",
    "zodiac": "兔, 牛, 鸡, 马, 羊, 鼠, 马",
    "wave": "绿, 蓝, 绿, 绿, 红, 蓝, 红"
  },
  "hk": {
    "numbers": [
      8,
      28,
      46,
      37,
      36,
      33,
      4
    ],
    "issue": "2026019",
    "time": "2026-02-15 21:32:32",
    "zodiac": "猪, 兔, 鸡, 马, 羊, 狗, 兔",
    "wave": "红, 绿, 红, 蓝, 蓝, 绿, 蓝"
  }
}